anisette/__init__.py
anisette/__main__.py
anisette/_adi.py
anisette/_allocator.py
anisette/_ani_provider.py
anisette/_arch.py
anisette/_device.py
anisette/_fs.py
anisette/_hooks.py
anisette/_library.py
anisette/_session.py
anisette/_structs.py
anisette/_util.py
anisette/_vm.py
anisette/anisette.py
anisette/apple-root.pem
anisette/cli.py
anisette-1.2.4.dist-info/licenses/LICENSE
anisette-1.2.4.dist-info/METADATA
anisette-1.2.4.dist-info/WHEEL
anisette-1.2.4.dist-info/entry_points.txt
anisette-1.2.4.dist-info/top_level.txt
anisette-1.2.4.dist-info/RECORD
