Metadata-Version: 2.4
Name: Anisette
Version: 1.2.4
Summary: Anisette provider
Requires-Python: >=3.9
License-File: LICENSE
Requires-Dist: certifi>=2025.1.31
Requires-Dist: fs>=2.4.16
Requires-Dist: pyelftools>=0.31
Requires-Dist: typing-extensions>=4.12.2
Requires-Dist: unicorn>=2.1.1
Requires-Dist: urllib3>=2.3.0
Provides-Extra: cli
Requires-Dist: typer>=0.15.1; extra == "cli"
Requires-Dist: rich>=13.9.4; extra == "cli"
Dynamic: license-file
